FedexSDK/FedExSDK.py
FedexSDK/__init__.py
FedexSDK/models/AccountNumber.py
FedexSDK/models/Address.py
FedexSDK/models/Contact.py
FedexSDK/models/Recipient.py
FedexSDK/models/Request.py
FedexSDK/models/RequestedShipment.py
FedexSDK/models/Shipper.py
FedexSDK/models/SoldTo.py
FedexSDK/models/Tin.py
FedexSDK/models/TotalDeclaredValue.py
FedexSDK/models/__init__.py
FedexSDK/models/label/Barcode.py
FedexSDK/models/label/CompletedEtdDetail.py
FedexSDK/models/label/CompletedPackageDetail.py
FedexSDK/models/label/CompletedShipmentDetail.py
FedexSDK/models/label/DocumentRequirements.py
FedexSDK/models/label/GenerationDetail.py
FedexSDK/models/label/MasterTrackingId.py
FedexSDK/models/label/Name.py
FedexSDK/models/label/OperationalDetail.py
FedexSDK/models/label/OperationalInsturaction.py
FedexSDK/models/label/PackageDocument.py
FedexSDK/models/label/Part.py
FedexSDK/models/label/PieceResponse.py
FedexSDK/models/label/Response.py
FedexSDK/models/label/ServiceDescription.py
FedexSDK/models/label/ShipmentDocument.py
FedexSDK/models/label/TrackingId.py
FedexSDK/models/label/UploadDocumentReferenceDetail.py
FedexSDK/models/label/__init__.py
FedexSDK/models/tracking/AdditionalTrackingInfo.py
FedexSDK/models/tracking/Address.py
FedexSDK/models/tracking/DateAndTime.py
FedexSDK/models/tracking/DelayDetail.py
FedexSDK/models/tracking/DeliveryDetails.py
FedexSDK/models/tracking/DeliveryOptionEligiblityDetail.py
FedexSDK/models/tracking/Destination.py
FedexSDK/models/tracking/LatestStatusDetail.py
FedexSDK/models/tracking/LocationContactAndAddress.py
FedexSDK/models/tracking/OriginLocation.py
FedexSDK/models/tracking/PackageDetails.py
FedexSDK/models/tracking/RecipientInformation.py
FedexSDK/models/tracking/ScanEvent.py
FedexSDK/models/tracking/ScanLocation.py
FedexSDK/models/tracking/ServiceCommitMessage.py
FedexSDK/models/tracking/ServiceDetail.py
FedexSDK/models/tracking/ShipmentDetails.py
FedexSDK/models/tracking/ShipperInformation.py
FedexSDK/models/tracking/SpecialHandling.py
fedex_sdk-1.1.7.dist-info/METADATA
fedex_sdk-1.1.7.dist-info/WHEEL
fedex_sdk-1.1.7.dist-info/top_level.txt
fedex_sdk-1.1.7.dist-info/RECORD
