Metadata-Version: 2.2
Name: fedex-sdk
Version: 1.1.7
Summary: Fedex Label Create SDK
Author: Esat Yılmaz
Author-email: esatyilmaz3500@gmail.com
Classifier: Programming Language :: Python :: 3.9
Classifier: License :: OSI Approved :: MIT License
Classifier: Operating System :: OS Independent
Requires-Python: >=3.8
Dynamic: author
Dynamic: author-email
Dynamic: classifier
Dynamic: requires-python
Dynamic: summary
